{"Version":"1.0.0.0","LastState":3,"Modules":[{"ValidatedSteerId":20,"ValidatedDriveId":11,"ValidatedEncoderId":40,"IsEncoderOffsetConfigured":true,"IsDeviceSelectionCompleted":true,"IsConfigurationCompleted":true,"ModuleName":"Front Left","ModuleId":0,"Encoder":{"Id":40,"Name":"CANCoder (Device ID 40)","Model":"CANCoder","CANbus":"rio","CANbusFriendly":""},"SteerMotor":{"Id":20,"Name":"BackLeftAngle","Model":"Talon FX","CANbus":"rio","CANbusFriendly":""},"DriveMotor":{"Id":11,"Name":"FrontLeftAngle","Model":"Talon FX","CANbus":"rio","CANbusFriendly":""},"IsSteerInverted":false,"EncoderOffset":0.031494140625,"DriveMotorSelectionState":1,"SteerMotorSelectionState":1,"SteerEncoderSelectionState":1,"IsModuleValidationComplete":true},{"ValidatedSteerId":21,"ValidatedDriveId":22,"ValidatedEncoderId":30,"IsEncoderOffsetConfigured":true,"IsDeviceSelectionCompleted":true,"IsConfigurationCompleted":true,"ModuleName":"Front Right","ModuleId":1,"Encoder":{"Id":30,"Name":"CANCoder (Device ID 30)","Model":"CANCoder","CANbus":"rio","CANbusFriendly":""},"SteerMotor":{"Id":21,"Name":"Talon FX (Device ID 21)","Model":"Talon FX","CANbus":"rio","CANbusFriendly":""},"DriveMotor":{"Id":22,"Name":"Talon FX (Device ID 22)","Model":"Talon FX","CANbus":"rio","CANbusFriendly":""},"IsSteerInverted":false,"EncoderOffset":-0.044921875,"DriveMotorSelectionState":1,"SteerMotorSelectionState":1,"SteerEncoderSelectionState":1,"IsModuleValidationComplete":true},{"ValidatedSteerId":12,"ValidatedDriveId":32,"ValidatedEncoderId":10,"IsEncoderOffsetConfigured":true,"IsDeviceSelectionCompleted":true,"IsConfigurationCompleted":true,"ModuleName":"Back Left","ModuleId":2,"Encoder":{"Id":10,"Name":"CANCoder (Device ID 10)","Model":"CANCoder","CANbus":"rio","CANbusFriendly":""},"SteerMotor":{"Id":12,"Name":"FrontLeftDrive","Model":"Talon FX","CANbus":"rio","CANbusFriendly":""},"DriveMotor":{"Id":32,"Name":"BackRightDrive","Model":"Talon FX","CANbus":"rio","CANbusFriendly":""},"IsSteerInverted":false,"EncoderOffset":-0.2763671875,"DriveMotorSelectionState":1,"SteerMotorSelectionState":1,"SteerEncoderSelectionState":1,"IsModuleValidationComplete":true},{"ValidatedSteerId":31,"ValidatedDriveId":3,"ValidatedEncoderId":50,"IsEncoderOffsetConfigured":true,"IsDeviceSelectionCompleted":true,"IsConfigurationCompleted":true,"ModuleName":"Back Right","ModuleId":3,"Encoder":{"Id":50,"Name":"CANCoder (Device ID 50)","Model":"CANCoder","CANbus":"rio","CANbusFriendly":""},"SteerMotor":{"Id":31,"Name":"BackRightAngle","Model":"Talon FX","CANbus":"rio","CANbusFriendly":""},"DriveMotor":{"Id":3,"Name":"BackLeftDrive","Model":"Talon FX","CANbus":"rio","CANbusFriendly":""},"IsSteerInverted":false,"EncoderOffset":-0.23583984375,"DriveMotorSelectionState":1,"SteerMotorSelectionState":1,"SteerEncoderSelectionState":1,"IsModuleValidationComplete":true}],"SwerveOptions":{"IsValidConfiguration":true,"Gyro":{"Id":1,"Name":"Pigeon 2","Model":"Pigeon 2","CANbus":"rio","CANbusFriendly":""},"IsValidGyroCANbus":true,"VerticalTrackSizeInches":12.75,"HorizontalTrackSizeInches":13.1875,"WheelRadiusInches":1.925,"IsLeftSideInverted":false,"IsRightSideInverted":true,"SwerveModuleType":-1,"SwerveModuleConfiguration":{"_CouplingRatio":0.0,"_CustomName":null,"SteerRatio":12.8,"Flipped":-1,"DriveRatio":6.86,"CouplingRatio":0.0,"CustomName":null},"HasVerifiedSteer":false,"HasVerifiedDrive":false}}